MANIFEST.in
README.md
setup.py
NLP/__init__.py
NLP/five.py
NLP/four.py
NLP/one.py
NLP/three.py
NLP/two.py
SAQ/__init__.py
SAQ/one.py
daima/__init__.py
daima/j.py
daima/s.py
daima/v.py
daima/x.py
daima/z.py
resulttest.egg-info/PKG-INFO
resulttest.egg-info/SOURCES.txt
resulttest.egg-info/dependency_links.txt
resulttest.egg-info/requires.txt
resulttest.egg-info/top_level.txt
挂机程序无界面浏览器版/__init__.py
挂机程序无界面浏览器版/无界面浏览器.py